{
  "imdbId": "tt4429160",
  "title": "Red Shoes and the Seven Dwarfs",
  "releaseDate": "2020-09-18T00:00:00.000Z",
  "releaseYear": 2019,
  "posterFileName": "poster.jpg",
  "rated": "PG",
  "genres": ["Animation", "Action", "Adventure"],
  "directors": ["Hong Sung-ho", "Moo-Hyun Jang", "Young Sik Uhm"],
  "writers": ["WoongSub Ahn", "WooChul Jung", "ChangWon Kim"],
  "actors": ["Chloë Grace Moretz", "Sam Claflin", "Gina Gershon"],
  "runTime": 92,
  "plot": "Princes who have been turned into Dwarfs seek the red shoes of a lady in order to break the spell, although it will not be easy. A parody with a twist.",
  "subtitleIds": ["1de0cbf5", "d7f5c75b", "4b91d3e4", "61c6192b", "11133f58", "ee942aae"],
  "lastSynced": "2024-10-28T00:34:31.918Z",
  "lastModified": "2024-10-28T00:34:31.918Z"
}
